<?xml version="1.0" encoding="utf-8" ?><dwsync><file name="album-compact.php" server="rogerwilliamsart.com" local="3393792540" remote="16278694428" /><file name="album-extend.php" server="rogerwilliamsart.com" local="3393792540" remote="16278694428" /><file name="gallery-caption.php" server="rogerwilliamsart.com" local="3393792540" remote="16278694428" /><file name="gallery-carousel.php" server="rogerwilliamsart.com" local="3393792540" remote="16278694428" /><file name="gallery.php" server="rogerwilliamsart.com" local="3393792540" remote="16278694428" /><file name="imagebrowser-caption.php" server="rogerwilliamsart.com" local="3393792540" remote="16278694428" /><file name="imagebrowser-exif.php" server="rogerwilliamsart.com" local="3393792540" remote="16278694428" /><file name="imagebrowser.php" server="rogerwilliamsart.com" local="3393792540" remote="16278694428" /><file name="singlepic.php" server="rogerwilliamsart.com" local="3393792540" remote="16278694428" /></dwsync>