<?xml version="1.0" encoding="utf-8" ?><dwsync><file name="function.js" server="rogerwilliamsart.com" local="3393793860" remote="16278695748" /><file name="jquery.ad-gallery.js" server="rogerwilliamsart.com" local="3393793860" remote="16278695748" /><file name="jquery.ad-gallery.pack.js" server="rogerwilliamsart.com" local="3393793860" remote="16278695748" /><file name="jquery.min.js" server="rogerwilliamsart.com" local="3393793860" remote="16278695748" /><file name="jquery.nivo.slider.pack.js" server="rogerwilliamsart.com" local="3393793860" remote="16278695748" /><file name="left.gif" server="rogerwilliamsart.com" local="3393793860" remote="16278695748" /><file name="lightbox.js" server="rogerwilliamsart.com" local="3395218800" remote="16280120688" /><file name="script.js" server="rogerwilliamsart.com" local="3393793860" remote="16278695748" /><file name="simplegallery.js" server="rogerwilliamsart.com" local="3393793860" remote="16278695748" /></dwsync>